togger/__init__.py
togger-24.10.5a1.dist-info/METADATA
togger-24.10.5a1.dist-info/WHEEL
togger-24.10.5a1.dist-info/licenses/LICENSE
togger-24.10.5a1.dist-info/RECORD
