Metadata-Version: 2.3
Name: togger
Version: 24.10.5a1
Summary: A python logging frontend using T-Strings
Project-URL: Github, https://github.com/fried/togger
Project-URL: Issues, https://github.com/fried/togger/issues
Author-email: Jason Fried <me@jasonfried.info>
License-File: LICENSE
Classifier: Intended Audience :: Developers
Classifier: License :: OSI Approved :: MIT License
Classifier: Operating System :: OS Independent
Classifier: Programming Language :: Python :: 3
Classifier: Topic :: Software Development :: Libraries :: Python Modules
Classifier: Topic :: System :: Logging
Requires-Python: >=3.14
